energycap/__init__.py
energycap/sdk/__init__.py
energycap/sdk/energy_cap_api.py
energycap/sdk/version.py
energycap/sdk/models/__init__.py
energycap/sdk/models/abnormal_bill_cost_with_outlier_analysis_setting_request.py
energycap/sdk/models/abnormal_bill_cost_with_outlier_analysis_setting_request_py3.py
energycap/sdk/models/abnormal_bill_cost_with_outlier_analysis_setting_response.py
energycap/sdk/models/abnormal_bill_cost_with_outlier_analysis_setting_response_py3.py
energycap/sdk/models/abnormal_bill_demand_with_outlier_analysis_setting_request.py
energycap/sdk/models/abnormal_bill_demand_with_outlier_analysis_setting_request_py3.py
energycap/sdk/models/abnormal_bill_demand_with_outlier_analysis_setting_response.py
energycap/sdk/models/abnormal_bill_demand_with_outlier_analysis_setting_response_py3.py
energycap/sdk/models/abnormal_bill_use_with_outlier_analysis_setting_request.py
energycap/sdk/models/abnormal_bill_use_with_outlier_analysis_setting_request_py3.py
energycap/sdk/models/abnormal_bill_use_with_outlier_analysis_setting_response.py
energycap/sdk/models/abnormal_bill_use_with_outlier_analysis_setting_response_py3.py
energycap/sdk/models/account_alert_request.py
energycap/sdk/models/account_alert_request_py3.py
energycap/sdk/models/account_alert_response.py
energycap/sdk/models/account_alert_response_py3.py
energycap/sdk/models/account_audit_enable.py
energycap/sdk/models/account_audit_enable_py3.py
energycap/sdk/models/account_child.py
energycap/sdk/models/account_child_py3.py
energycap/sdk/models/account_child_with_type.py
energycap/sdk/models/account_child_with_type_py3.py
energycap/sdk/models/account_code_history_child.py
energycap/sdk/models/account_code_history_child_py3.py
energycap/sdk/models/account_code_history_request.py
energycap/sdk/models/account_code_history_request_py3.py
energycap/sdk/models/account_code_history_response.py
energycap/sdk/models/account_code_history_response_py3.py
energycap/sdk/models/account_connection_status_response.py
EnergyCapSdk-8.2301.4456.dist-info/METADATA
EnergyCapSdk-8.2301.4456.dist-info/WHEEL
EnergyCapSdk-8.2301.4456.dist-info/top_level.txt
EnergyCapSdk-8.2301.4456.dist-info/RECORD
