Metadata-Version: 2.1
Name: EnergyCapSdk
Version: 8.2301.4456
Summary: EnergyCapApi
Home-page: UNKNOWN
Author: UNKNOWN
Author-email: UNKNOWN
License: UNKNOWN
Keywords: Swagger,EnergyCapApi
Platform: UNKNOWN
Requires-Dist: msrest (>=0.5.2)
